test/__init__.py
test/test_znop.py
znop/__init__.py
znop/app.py
znop/core.py
znop/exceptions.py
znop-0.2.0.dist-info/LICENSE
znop-0.2.0.dist-info/METADATA
znop-0.2.0.dist-info/WHEEL
znop-0.2.0.dist-info/entry_points.txt
znop-0.2.0.dist-info/top_level.txt
znop-0.2.0.dist-info/zip-safe
znop-0.2.0.dist-info/RECORD
