Metadata-Version: 2.1
Name: znop
Version: 0.2.0
Summary: Library that solves discrete math operations of the group Zn, provides both as calculator program or third party library.
Home-page: https://github.com/paaksing/Znop
Author: Paaksing
Author-email: paaksingtech@gmail.com
License: MIT
Keywords: Math,Discrete,Group mod n,Int mod n,Zn
Platform: UNKNOWN
Classifier: Development Status :: 4 - Beta
Classifier: Programming Language :: Python :: 3.6
Classifier: Environment :: Console
Classifier: Operating System :: OS Independent
Classifier: Intended Audience :: Education
Classifier: License :: OSI Approved :: MIT License
Classifier: Topic :: Scientific/Engineering :: Mathematics
Classifier: Topic :: Software Development :: Libraries :: Python Modules
Classifier: Natural Language :: English
Requires-Dist: wheel
